MANIFEST.in
README.md
setup.py
miller_alaskamoho_srl2018/__init__.py
miller_alaskamoho_srl2018/__main__.py
miller_alaskamoho_srl2018.egg-info/PKG-INFO
miller_alaskamoho_srl2018.egg-info/SOURCES.txt
miller_alaskamoho_srl2018.egg-info/dependency_links.txt
miller_alaskamoho_srl2018.egg-info/requires.txt
miller_alaskamoho_srl2018.egg-info/top_level.txt
miller_alaskamoho_srl2018/Models/AlaskaHeatFlow.npz
miller_alaskamoho_srl2018/Models/AlaskaHeatFlowErrs.npz
miller_alaskamoho_srl2018/Models/AlaskaHeatFlowFineGrid.npz
miller_alaskamoho_srl2018/Models/AlaskaMoHiErrs-AlaskaMohoFineGrid.npz
miller_alaskamoho_srl2018/Models/AlaskaMoHiErrs.npz
miller_alaskamoho_srl2018/Models/AlaskaMoLoErrs-AlaskaMohoFineGrid.npz
miller_alaskamoho_srl2018/Models/AlaskaMoLoErrs.npz
miller_alaskamoho_srl2018/Models/AlaskaMoho.npz
miller_alaskamoho_srl2018/Models/AlaskaMohoErrs-AlaskaMohoFineGrid.npz
miller_alaskamoho_srl2018/Models/AlaskaMohoErrs.npz
miller_alaskamoho_srl2018/Notebooks/A0-Index.ipynb
miller_alaskamoho_srl2018/Notebooks/A1 - Raw data, convert and save.ipynb
miller_alaskamoho_srl2018/Notebooks/A2 - Raw data - plot quality information.ipynb
miller_alaskamoho_srl2018/Notebooks/A3 - Triangulating and interpolating raw data.ipynb
miller_alaskamoho_srl2018/Notebooks/A4 - Plotting moho and moho slope.ipynb
miller_alaskamoho_srl2018/Notebooks/A5 - Interactive 3D plot.ipynb
miller_alaskamoho_srl2018/Notebooks/A6 - Convert Models to Regular XYZ grid.ipynb
miller_alaskamoho_srl2018/Notebooks/Untitled.ipynb
miller_alaskamoho_srl2018/Notebooks/Figures/ErrorsAndScores.png
miller_alaskamoho_srl2018/Notebooks/Figures/MohoSurfaceGradient-ClusteredGrids.png
miller_alaskamoho_srl2018/Notebooks/ModelConstruction/B1 - Alaska-Moho-Data-Raw-Triangulation.ipynb
miller_alaskamoho_srl2018/Notebooks/ModelConstruction/B2 - Estimating model predictive capacity.ipynb
miller_alaskamoho_srl2018/Notebooks/ModelConstruction/B3 - Alaska-Moho-Mapping-To-Improved-Triangulation-Scored.ipynb
miller_alaskamoho_srl2018/Notebooks/ModelConstruction/B4 - Effect of outliers.ipynb
miller_alaskamoho_srl2018/Notebooks/ModelConstruction/Data/Moho-Alaska/picks_1999-Apr2018_clean.txt
miller_alaskamoho_srl2018/documentation/__init__.py