Metadata-Version: 2.1
Name: miller-alaskamoho-srl2018
Version: 1.0
Summary: Python interface to Miller SRL 2018 Alaska Moho model - requires stripy
Home-page: UNKNOWN
Author: Louis Moresi
Author-email: louis.moresi@unimelb.edu.au
License: UNKNOWN
Platform: UNKNOWN
